TPJLang/__init__.py
TPJLang/main.py
tpjl-2021.4.4.dist-info/METADATA
tpjl-2021.4.4.dist-info/WHEEL
tpjl-2021.4.4.dist-info/top_level.txt
tpjl-2021.4.4.dist-info/RECORD
