Metadata-Version: 2.1
Name: tpjl
Version: 2021.4.4
Summary: a free & OpenSource Portable version of JSON.
Home-page: https://github.com/TechGeeks-Dev/PJSONLang
Author: TechGeeks
Author-email: PJSONLang@tgeeks.cf
Maintainer: Rajdeep Malakar
Maintainer-email: Rajdeep@tgeeks.cf
License: UNKNOWN
Platform: UNKNOWN
Classifier: Programming Language :: Python :: 3
Classifier: License :: OSI Approved :: MIT License
Classifier: Operating System :: OS Independent
Requires-Python: >=3.6
